{
  "version": 8,
  "name": "Empty Style",
  "metadata": {
    "maputnik:renderer": "mbgljs"
  },
  "sources": {
    "5vjyz55i1": {
      "type": "vector",
      "tiles": [
        "http://localhost:5173/data/tiles/{z}/{x}/{y}.pbf"
      ],
      "minZoom": 0,
      "maxZoom": 22
    },
    "5vjyz55i1gt": {
      "type": "vector",
      "tiles": [
        "http://localhost:5173/data/tiles/{z}/{x}/{y}.pbf"
      ],
      "minZoom": 0,
      "maxZoom": 22
    },
    "natural_earth_shaded_relief": {
      "maxzoom": 22,
      "tileSize": 256,
      "tiles": [
        "https://server.arcgisonline.com/ArcGIS/rest/services/World_Topo_Map/MapServer/tile/{z}/{y}/{x}"
      ],
      "type": "raster"
    }
  },
  "sprite": "",
  "glyphs": "https://orangemug.github.io/font-glyphs/glyphs/{fontstack}/{range}.pbf",
  "layers": [
    {
      "id": "natural_earth",
      "type": "raster",
      "source": "natural_earth_shaded_relief",
      "maxzoom": 22,
      "paint": {
        "raster-opacity": {
          "base": 1.5,
          "stops": [
            [
              0,
              0.6
            ],
            [
              6,
              0.6
            ]
          ]
        }
      }
    },
    {
      "id": "my_point",
      "type": "circle",
      "source": "5vjyz55i1",
      "source-layer": "data",
      "paint": {
        "circle-radius": 5,
        "circle-stroke-color": "rgba(0, 0, 0, 1)",
        "circle-color": "rgba(255, 255, 255, 1)",
        "circle-stroke-width": 1
      }
    },
    {
      "id": "my_point_github",
      "type": "circle",
      "source": "5vjyz55i1gt",
      "source-layer": "data",
      "paint": {
        "circle-radius": 5,
        "circle-stroke-color": "rgba(0, 0, 0, 1)",
        "circle-color": "rgba(255, 255, 255, 1)",
        "circle-stroke-width": 1
      }
    }
  ],
  "id": "qiko9zfl7"
}